langval/__init__.py
langval/_decorator.py
langval/_prompt.py
langval/_utils.py
langval/test_case.py
langval/error/__init__.py
langval/eval/__init__.py
langval/eval/base.py
langval/eval/langchain.py
langval/model/__init__.py
langval/tools/__init__.py
langval-0.0.3.dist-info/METADATA
langval-0.0.3.dist-info/WHEEL
langval-0.0.3.dist-info/licenses/LICENSE
langval-0.0.3.dist-info/RECORD
