Metadata-Version: 2.3
Name: langval
Version: 0.0.3
Summary: Langval is a language model evaluation tool for evaluating the toxicity, accuracy, hallucination, and bias of language models.
Author-email: Vasanth Kumar <itsparser@gmail.com>, Adheeban <iamadhee@gmail.com>
License-File: LICENSE
Requires-Python: >=3.12
Requires-Dist: langchain-core>=0.3.5
Requires-Dist: langchain-ollama>=0.2.0
Requires-Dist: langchain>=0.3.0
Requires-Dist: langgraph>=0.2.26
Requires-Dist: pytest>=8.3.3
